elanwriter/__init__.py
elanwriter-0.0.0.dev2.dist-info/LICENSE
elanwriter-0.0.0.dev2.dist-info/METADATA
elanwriter-0.0.0.dev2.dist-info/WHEEL
elanwriter-0.0.0.dev2.dist-info/top_level.txt
elanwriter-0.0.0.dev2.dist-info/RECORD
